{
  "name": "meygioh-k05n1ib",
  "arn": "arn:aws:iam::443111828386:role/meygioh-k05n1ib",
  "service": [
    "lambda.amazonaws.com"
  ],
  "policy": {
    "Version": "2012-10-17",
    "Statement": [
      {
        "Effect": "Allow",
        "Resource": "*",
        "Action": [
          "logs:CreateLogGroup",
          "logs:CreateLogStream",
          "logs:PutLogEvents"
        ]
      },
      {
        "Effect": "Allow",
        "Resource": "arn:aws:s3:::meygioh-iyo3nt/*",
        "Action": [
          "s3:GetObject",
          "s3:PutObject"
        ]
      },
      {
        "Effect": "Allow",
        "Resource": "arn:aws:sqs:us-east-1:443111828386:meygioh-iyo3nt.fifo",
        "Action": [
          "sqs:SendMessage"
        ]
      },
      {
        "Effect": "Allow",
        "Resource": "arn:aws:sqs:us-east-1:443111828386:meygioh-iyo3nt.fifo",
        "Action": [
          "sqs:ReceiveMessage",
          "sqs:DeleteMessage",
          "sqs:GetQueueAttributes"
        ]
      }
    ]
  },
  "region": "us-east-1"
}